{
  "project_info": {
    "project_number": "422427273698",
    "firebase_url": "https://visapay-fef6e.firebaseio.com",
    "project_id": "visapay-fef6e",
    "storage_bucket": "visapay-fef6e.appspot.com"
  },
  "client": [
    {
      "client_info": {
        "mobilesdk_app_id": "1:422427273698:android:56f175bc956178c01fb1bb",
        "android_client_info": {
          "package_name": "com.example.android.visapay"
        }
      },
      "oauth_client": [
        {
          "client_id": "422427273698-fmso6bii0e5biepu519ugc0pv5c2u2ai.apps.googleusercontent.com",
          "client_type": 1,
          "android_info": {
            "package_name": "com.example.android.visapay",
            "certificate_hash": "738ed68cb5dcd66d4c3e819c7688f1d9ef649a10"
          }
        },
        {
          "client_id": "422427273698-0jadci72b19rurij28k63vo9r4njvccc.apps.googleusercontent.com",
          "client_type": 3
        }
      ],
      "api_key": [
        {
          "current_key": "AIzaSyCGH8Xa7oU3_KeFh7cwn1xdkckdYPbFr8Y"
        }
      ],
      "services": {
        "appinvite_service": {
          "other_platform_oauth_client": [
            {
              "client_id": "422427273698-0jadci72b19rurij28k63vo9r4njvccc.apps.googleusercontent.com",
              "client_type": 3
            }
          ]
        }
      }
    }
  ],
  "configuration_version": "1"
}